[
  {
    "model": "judge.Course",
    "fields": {
      "name": "Math4Business",
      "master": null,
      "ECTS": 9,
      "semester": 5,
      "location": "Paris 14e, 9 rue Dareau"
    }
  },
  {
    "model": "judge.Course",
    "fields": {
      "name": "Data Driven Optimization",
      "master": null,
      "ECTS": 5,
      "semester": 5,
      "location": "Ponts"
    }
  },
    {
    "model": "judge.Course",
    "fields": {
      "name": "Algo de Monte-Carlo par chaînes de Markov et méthodes particulaires",
      "master": null,
      "ECTS": 6,
      "semester": 5,
      "location": "Jussieu"
    }
  }
]